webint_mentions/__init__.py
webint_mentions/templates/__init__.py
webint_mentions/templates/index.html
webint_mentions/templates/received/__init__.py
webint_mentions/templates/received/index.html
webint_mentions/templates/sent/__init__.py
webint_mentions-0.0.16.dist-info/METADATA
webint_mentions-0.0.16.dist-info/entry_points.txt
webint_mentions-0.0.16.dist-info/WHEEL
webint_mentions-0.0.16.dist-info/RECORD
